<?xml version = '1.0' encoding = 'UTF-8'?>
<Relation class="oracle.dbtools.crest.model.design.logical.Relation" name="fk_rsrc_roles" directorySegmentName="seg_1" id="FBAF6964-1F5A-B139-A950-D8F0ECB0B74A">
<createdBy>administrator</createdBy>
<createdTime>2013-06-01 11:57:34 UTC</createdTime>
<generatorID>1261869F-D6D4-ED78-44A8-F0A9F2AA5F97</generatorID>
<ownerDesignName>primavera</ownerDesignName>
<engineerTo>
<item key="F3498740-FDC8-7B45-3226-1B46885514C6" value="true"/>
</engineerTo>
<sourcePk>55991B30-ACDA-06BB-A118-D96A84A79653</sourcePk>
<identifying>false</identifying>
<optionalSource>true</optionalSource>
<optionalTarget>true</optionalTarget>
<sourceCardinality>1</sourceCardinality>
<sourceEntity>6A366382-82FA-24CC-6C00-EB99708BACE6</sourceEntity>
<targetCardinalityString>*</targetCardinalityString>
<targetEntity>8115915A-34CF-7153-FE3E-30E887C61B95</targetEntity>
<transferable>true</transferable>
<deleteRule>NO ACTION</deleteRule>
</Relation>