<?xml version = '1.0' encoding = 'UTF-8'?>
<TableProxySqlServerv2k5 class="oracle.dbtools.crest.model.design.storage.sqlserver.v2k5.TableProxySqlServerv2k5" name="Mögliche Hersteller Geräte" directorySegmentName="seg_1" id="6409E0E9-0C9C-4824-4DDE-0D9B5FB90A0F">
<createdBy>administrator</createdBy>
<createdTime>2013-06-01 20:48:41 UTC</createdTime>
<generatorID>Benutzergeneriert</generatorID>
<ownerDesignName>Feuerwehr</ownerDesignName>
<database>F81FDDCF-4017-BB00-383F-C205C31E9D1E</database>
<filegroup>88A39397-675F-545E-B5D1-86C0A67E7855</filegroup>
<schema>612B09AB-F869-F6FA-26A6-9FEC143B09C0</schema>
<columnProxies>
<ColumnProxy class="oracle.dbtools.crest.model.design.storage.sqlserver.v2k5.ColumnProxySqlServerv2k5" name="Text3" id="29038B58-D426-4AD7-3714-B0EE1D3F1FA9">
<createdBy>administrator</createdBy>
<createdTime>2013-06-01 20:48:41 UTC</createdTime>
<generatorID>Benutzergeneriert</generatorID>
<ownerDesignName>Feuerwehr</ownerDesignName>
<collation>Latin1_General_CI_AS</collation>
</ColumnProxy>
<ColumnProxy class="oracle.dbtools.crest.model.design.storage.sqlserver.v2k5.ColumnProxySqlServerv2k5" name="Zahl4" id="3C16B9D9-5B55-AE04-7074-3B2924A1DAFB">
<createdBy>administrator</createdBy>
<createdTime>2013-06-01 20:48:41 UTC</createdTime>
<generatorID>Benutzergeneriert</generatorID>
<ownerDesignName>Feuerwehr</ownerDesignName>
</ColumnProxy>
<ColumnProxy class="oracle.dbtools.crest.model.design.storage.sqlserver.v2k5.ColumnProxySqlServerv2k5" name="JaNein2" id="4B294724-8B9F-AC22-C89D-8231A0AD136B">
<createdBy>administrator</createdBy>
<createdTime>2013-06-01 20:48:41 UTC</createdTime>
<generatorID>Benutzergeneriert</generatorID>
<ownerDesignName>Feuerwehr</ownerDesignName>
</ColumnProxy>
<ColumnProxy class="oracle.dbtools.crest.model.design.storage.sqlserver.v2k5.ColumnProxySqlServerv2k5" name="Text2" id="8050F80D-710B-6B99-EF4C-3A919DF43ECE">
<createdBy>administrator</createdBy>
<createdTime>2013-06-01 20:48:41 UTC</createdTime>
<generatorID>Benutzergeneriert</generatorID>
<ownerDesignName>Feuerwehr</ownerDesignName>
<collation>Latin1_General_CI_AS</collation>
</ColumnProxy>
<ColumnProxy class="oracle.dbtools.crest.model.design.storage.sqlserver.v2k5.ColumnProxySqlServerv2k5" name="Text4" id="86F1CD8B-0036-AF62-7FB8-8CA7C40349C0">
<createdBy>administrator</createdBy>
<createdTime>2013-06-01 20:48:41 UTC</createdTime>
<generatorID>Benutzergeneriert</generatorID>
<ownerDesignName>Feuerwehr</ownerDesignName>
<collation>Latin1_General_CI_AS</collation>
</ColumnProxy>
<ColumnProxy class="oracle.dbtools.crest.model.design.storage.sqlserver.v2k5.ColumnProxySqlServerv2k5" name="Hersteller" id="9447AC58-5CC7-2531-F55D-625AFBCE5A64">
<createdBy>administrator</createdBy>
<createdTime>2013-06-01 20:48:41 UTC</createdTime>
<generatorID>Benutzergeneriert</generatorID>
<ownerDesignName>Feuerwehr</ownerDesignName>
<collation>Latin1_General_CI_AS</collation>
</ColumnProxy>
<ColumnProxy class="oracle.dbtools.crest.model.design.storage.sqlserver.v2k5.ColumnProxySqlServerv2k5" name="JaNein1" id="A04B77A4-1CE9-8D79-13EA-296CFE3CCD4D">
<createdBy>administrator</createdBy>
<createdTime>2013-06-01 20:48:41 UTC</createdTime>
<generatorID>Benutzergeneriert</generatorID>
<ownerDesignName>Feuerwehr</ownerDesignName>
</ColumnProxy>
<ColumnProxy class="oracle.dbtools.crest.model.design.storage.sqlserver.v2k5.ColumnProxySqlServerv2k5" name="Zahl5" id="A97719BF-BBE5-DC10-1BE8-F3163A67C9EC">
<createdBy>administrator</createdBy>
<createdTime>2013-06-01 20:48:41 UTC</createdTime>
<generatorID>Benutzergeneriert</generatorID>
<ownerDesignName>Feuerwehr</ownerDesignName>
</ColumnProxy>
<ColumnProxy class="oracle.dbtools.crest.model.design.storage.sqlserver.v2k5.ColumnProxySqlServerv2k5" name="Zahl2" id="AD1509F1-DCB1-2D47-6A23-9942C86D76BB">
<createdBy>administrator</createdBy>
<createdTime>2013-06-01 20:48:41 UTC</createdTime>
<generatorID>Benutzergeneriert</generatorID>
<ownerDesignName>Feuerwehr</ownerDesignName>
</ColumnProxy>
<ColumnProxy class="oracle.dbtools.crest.model.design.storage.sqlserver.v2k5.ColumnProxySqlServerv2k5" name="Text1" id="C2B41B4F-81C8-2F59-F030-C1283D063B54">
<createdBy>administrator</createdBy>
<createdTime>2013-06-01 20:48:41 UTC</createdTime>
<generatorID>Benutzergeneriert</generatorID>
<ownerDesignName>Feuerwehr</ownerDesignName>
<collation>Latin1_General_CI_AS</collation>
</ColumnProxy>
<ColumnProxy class="oracle.dbtools.crest.model.design.storage.sqlserver.v2k5.ColumnProxySqlServerv2k5" name="Zahl3" id="C7833EA1-55A9-145B-A3B5-AF1FA4DE89C4">
<createdBy>administrator</createdBy>
<createdTime>2013-06-01 20:48:41 UTC</createdTime>
<generatorID>Benutzergeneriert</generatorID>
<ownerDesignName>Feuerwehr</ownerDesignName>
</ColumnProxy>
<ColumnProxy class="oracle.dbtools.crest.model.design.storage.sqlserver.v2k5.ColumnProxySqlServerv2k5" name="Zahl1" id="D68A48F7-1F4E-DB1C-CEDE-CC49025D16B1">
<createdBy>administrator</createdBy>
<createdTime>2013-06-01 20:48:41 UTC</createdTime>
<generatorID>Benutzergeneriert</generatorID>
<ownerDesignName>Feuerwehr</ownerDesignName>
</ColumnProxy>
<ColumnProxy class="oracle.dbtools.crest.model.design.storage.sqlserver.v2k5.ColumnProxySqlServerv2k5" name="Datum1" id="E853F32F-050E-3A77-6704-2F5012159069">
<createdBy>administrator</createdBy>
<createdTime>2013-06-01 20:48:41 UTC</createdTime>
<generatorID>Benutzergeneriert</generatorID>
<ownerDesignName>Feuerwehr</ownerDesignName>
</ColumnProxy>
<ColumnProxy class="oracle.dbtools.crest.model.design.storage.sqlserver.v2k5.ColumnProxySqlServerv2k5" name="Datum2" id="F697FB43-EA67-DCA2-39F8-931AAC887EB6">
<createdBy>administrator</createdBy>
<createdTime>2013-06-01 20:48:41 UTC</createdTime>
<generatorID>Benutzergeneriert</generatorID>
<ownerDesignName>Feuerwehr</ownerDesignName>
</ColumnProxy>
<ColumnProxy class="oracle.dbtools.crest.model.design.storage.sqlserver.v2k5.ColumnProxySqlServerv2k5" name="Text5" id="F99BD477-85BA-20D4-B84B-6895D6C1A9B9">
<createdBy>administrator</createdBy>
<createdTime>2013-06-01 20:48:41 UTC</createdTime>
<generatorID>Benutzergeneriert</generatorID>
<ownerDesignName>Feuerwehr</ownerDesignName>
<collation>Latin1_General_CI_AS</collation>
</ColumnProxy>
</columnProxies>
</TableProxySqlServerv2k5>