<?xml version = '1.0' encoding = 'UTF-8'?>
<FKIndexAssociation class="oracle.dbtools.crest.model.design.relational.FKIndexAssociation" directorySegmentName="seg_1" id="CF4E659D-0D5C-CB35-7352-B76231F60A71" name="fk_taskproc_project">
<sourceConnName>local</sourceConnName>
<sourceObjSchema>dbo</sourceObjSchema>
<sourceObjName>fk_taskproc_project</sourceObjName>
<createdBy>administrator</createdBy>
<createdTime>2013-06-01 11:22:31 UTC</createdTime>
<generatorID>Benutzergeneriert</generatorID>
<ownerDesignName>primavera</ownerDesignName>
<containerWithKeyObject>5C0D936F-82CC-AF5F-A3D1-09C0C11C2B65</containerWithKeyObject>
<deleteRule>NO ACTION</deleteRule>
<localFKIndex>D4B4DADC-57A1-4E8F-FA34-2B13F9A543CA</localFKIndex>
<keyObject>016D21CC-7B11-278B-2034-520003D705BE</keyObject>
<mandatory>true</mandatory>
<transferable>true</transferable>
<columnDependencyConstraintGenerateInDDL>true</columnDependencyConstraintGenerateInDDL>
</FKIndexAssociation>