<?xml version = '1.0' encoding = 'UTF-8'?>
<Relation class="oracle.dbtools.crest.model.design.logical.Relation" name="fk_prpfolio_projwbs" directorySegmentName="seg_0" id="CA20E2F2-3596-989A-1644-EEC6160080DC">
<createdBy>administrator</createdBy>
<createdTime>2013-06-01 11:57:34 UTC</createdTime>
<generatorID>36401831-696F-DE3F-F910-AA7D4FCCF6CF</generatorID>
<ownerDesignName>primavera</ownerDesignName>
<engineerTo>
<item key="F3498740-FDC8-7B45-3226-1B46885514C6" value="true"/>
</engineerTo>
<sourcePk>4B3A27F7-81BC-1902-E8CF-F58425A808AC</sourcePk>
<identifying>true</identifying>
<optionalSource>true</optionalSource>
<optionalTarget>false</optionalTarget>
<sourceCardinality>1</sourceCardinality>
<sourceEntity>47E5966E-FDD9-5A4E-66ED-D18CACDA2945</sourceEntity>
<targetCardinalityString>*</targetCardinalityString>
<targetEntity>6EBC640A-2BB9-04F5-1616-AD6F158ECEDD</targetEntity>
<transferable>true</transferable>
<deleteRule>NO ACTION</deleteRule>
</Relation>