<?xml version = '1.0' encoding = 'UTF-8'?>
<Relation class="oracle.dbtools.crest.model.design.logical.Relation" name="Relation_3" directorySegmentName="seg_0" id="B0AD7FF0-A633-D54B-581C-21694375D1FB">
<createdBy>peter</createdBy>
<createdTime>2013-06-02 08:25:32 UTC</createdTime>
<generatorID>Benutzergeneriert</generatorID>
<ownerDesignName>Feuerwehr</ownerDesignName>
<engineerTo>
<item key="2021CA32-568E-BB7B-FA9D-E84EF433D674" value="true"/>
</engineerTo>
<sourcePk>094090F4-9DEC-6342-9EBD-2713A77B22C1</sourcePk>
<identifying>false</identifying>
<nameOnTarget>Leitender</nameOnTarget>
<optionalSource>true</optionalSource>
<optionalTarget>true</optionalTarget>
<sourceCardinality>1</sourceCardinality>
<sourceEntity>C228A7EF-33A5-6C18-3544-BBB2FD465760</sourceEntity>
<targetCardinalityString>*</targetCardinalityString>
<targetEntity>4E167AA2-3B00-BF03-86C0-D004CD47ED57</targetEntity>
<transferable>true</transferable>
<deleteRule>NO ACTION</deleteRule>
</Relation>