<?xml version = '1.0' encoding = 'UTF-8'?>
<TableProxyOraclev9i class="oracle.dbtools.crest.model.design.storage.oracle.v9i.TableProxyOraclev9i" name="PhysicalCharacteristic" directorySegmentName="seg_0" id="73FCDAB2-E81A-8886-154E-8541B3AE71CD">
<createdBy>peter</createdBy>
<createdTime>2013-10-31 06:07:06 UTC</createdTime>
<generatorID>Benutzergeneriert</generatorID>
<ownerDesignName>pwdb</ownerDesignName>
<partitionedRowMovement>DISABLE</partitionedRowMovement>
<columnProxies>
<ColumnProxy class="oracle.dbtools.crest.model.design.storage.oracle.v9i.ColumnProxyOraclev9i" name="Gender" id="06AE193D-7682-A282-703E-B10D46ED662C">
<createdBy>peter</createdBy>
<createdTime>2013-10-31 06:07:06 UTC</createdTime>
<generatorID>Benutzergeneriert</generatorID>
<ownerDesignName>pwdb</ownerDesignName>
<defaultValue>NULL</defaultValue>
</ColumnProxy>
<ColumnProxy class="oracle.dbtools.crest.model.design.storage.oracle.v9i.ColumnProxyOraclev9i" name="Piercings" id="1B25F6F6-990C-DBE5-E636-FEEE68F75AEB">
<createdBy>peter</createdBy>
<createdTime>2013-10-31 06:07:06 UTC</createdTime>
<generatorID>Benutzergeneriert</generatorID>
<ownerDesignName>pwdb</ownerDesignName>
<defaultValue>NULL</defaultValue>
</ColumnProxy>
<ColumnProxy class="oracle.dbtools.crest.model.design.storage.oracle.v9i.ColumnProxyOraclev9i" name="Height" id="23E8D66A-BC83-2C00-3BF8-B06A70B1AC0D">
<createdBy>peter</createdBy>
<createdTime>2013-10-31 06:07:06 UTC</createdTime>
<generatorID>Benutzergeneriert</generatorID>
<ownerDesignName>pwdb</ownerDesignName>
</ColumnProxy>
<ColumnProxy class="oracle.dbtools.crest.model.design.storage.oracle.v9i.ColumnProxyOraclev9i" name="Weight" id="3CD06CFF-7DFB-5E8B-DB74-61A16752E2BF">
<createdBy>peter</createdBy>
<createdTime>2013-10-31 06:07:06 UTC</createdTime>
<generatorID>Benutzergeneriert</generatorID>
<ownerDesignName>pwdb</ownerDesignName>
</ColumnProxy>
<ColumnProxy class="oracle.dbtools.crest.model.design.storage.oracle.v9i.ColumnProxyOraclev9i" name="ThroughDate" id="5D97D4F5-1393-243D-6C35-2B61F6619774">
<createdBy>peter</createdBy>
<createdTime>2013-10-31 06:07:06 UTC</createdTime>
<generatorID>Benutzergeneriert</generatorID>
<ownerDesignName>pwdb</ownerDesignName>
<defaultValue>NULL</defaultValue>
</ColumnProxy>
<ColumnProxy class="oracle.dbtools.crest.model.design.storage.oracle.v9i.ColumnProxyOraclev9i" name="PersonId" id="864DB561-9AB0-C221-BDE5-B322BAAF6EB1">
<createdBy>peter</createdBy>
<createdTime>2013-10-31 06:07:06 UTC</createdTime>
<generatorID>Benutzergeneriert</generatorID>
<ownerDesignName>pwdb</ownerDesignName>
</ColumnProxy>
<ColumnProxy class="oracle.dbtools.crest.model.design.storage.oracle.v9i.ColumnProxyOraclev9i" name="Tattoos" id="9C5BC599-D2F6-8CAF-DB86-9D74857A82DD">
<createdBy>peter</createdBy>
<createdTime>2013-10-31 06:07:06 UTC</createdTime>
<generatorID>Benutzergeneriert</generatorID>
<ownerDesignName>pwdb</ownerDesignName>
<defaultValue>NULL</defaultValue>
</ColumnProxy>
<ColumnProxy class="oracle.dbtools.crest.model.design.storage.oracle.v9i.ColumnProxyOraclev9i" name="FromDate" id="C5437858-09C3-D737-414C-7FABBEA93C71">
<createdBy>peter</createdBy>
<createdTime>2013-10-31 06:07:06 UTC</createdTime>
<generatorID>Benutzergeneriert</generatorID>
<ownerDesignName>pwdb</ownerDesignName>
</ColumnProxy>
<ColumnProxy class="oracle.dbtools.crest.model.design.storage.oracle.v9i.ColumnProxyOraclev9i" name="Id" id="C5A0DFE9-0EA2-5802-3C10-28FDB73633D3">
<createdBy>peter</createdBy>
<createdTime>2013-10-31 06:07:06 UTC</createdTime>
<generatorID>Benutzergeneriert</generatorID>
<ownerDesignName>pwdb</ownerDesignName>
</ColumnProxy>
<ColumnProxy class="oracle.dbtools.crest.model.design.storage.oracle.v9i.ColumnProxyOraclev9i" name="KEY" id="CAB3CBEA-AACD-DAA3-B7F3-3425A3E92E13">
<createdBy>peter</createdBy>
<createdTime>2013-10-31 06:07:06 UTC</createdTime>
<generatorID>Benutzergeneriert</generatorID>
<ownerDesignName>pwdb</ownerDesignName>
</ColumnProxy>
</columnProxies>
<foreignKeys>
<ForeignKey class="oracle.dbtools.crest.model.design.storage.oracle.v9i.FKProxyOraclev9i" name="FK_PC_P" id="C31321BE-8853-445B-F6E8-6CD87C03E212">
<createdBy>peter</createdBy>
<createdTime>2013-10-31 06:07:06 UTC</createdTime>
<generatorID>Benutzergeneriert</generatorID>
<ownerDesignName>pwdb</ownerDesignName>
</ForeignKey>
</foreignKeys>
<primaryKeys>
<PrimaryKey class="oracle.dbtools.crest.model.design.storage.oracle.v9i.PKProxyOraclev9i" name="PhysicalCharacteristic_PK" id="2FB86BA9-3670-288B-6464-680EDF40E4AE">
<createdBy>peter</createdBy>
<createdTime>2013-10-31 06:07:06 UTC</createdTime>
<generatorID>Benutzergeneriert</generatorID>
<ownerDesignName>pwdb</ownerDesignName>
<indexSort>SORTED</indexSort>
</PrimaryKey>
</primaryKeys>
</TableProxyOraclev9i>