<?xml version = '1.0' encoding = 'UTF-8'?>
<TableProxySqlServerv2k5 class="oracle.dbtools.crest.model.design.storage.sqlserver.v2k5.TableProxySqlServerv2k5" name="Druckluftflaschen" directorySegmentName="seg_0" id="47D10B95-3D01-5EDC-DEA5-349301DB5A4B">
<createdBy>peter</createdBy>
<createdTime>2015-04-07 07:49:31 UTC</createdTime>
<ownerDesignName>FeuerwehrDirect</ownerDesignName>
<database>DB_NULLELEMENT</database>
<columnProxies>
<ColumnProxy class="oracle.dbtools.crest.model.design.storage.sqlserver.v2k5.ColumnProxySqlServerv2k5" name="Zahl7" id="00DB38FD-5D53-E8AA-4F4D-8EE18D0B3941">
<createdBy>peter</createdBy>
<createdTime>2015-04-07 07:49:32 UTC</createdTime>
<ownerDesignName>FeuerwehrDirect</ownerDesignName>
</ColumnProxy>
<ColumnProxy class="oracle.dbtools.crest.model.design.storage.sqlserver.v2k5.ColumnProxySqlServerv2k5" name="Eigentümer" id="0703D7A7-E130-FE68-F984-7CA9FC6FADEA">
<createdBy>peter</createdBy>
<createdTime>2015-04-07 07:49:32 UTC</createdTime>
<ownerDesignName>FeuerwehrDirect</ownerDesignName>
</ColumnProxy>
<ColumnProxy class="oracle.dbtools.crest.model.design.storage.sqlserver.v2k5.ColumnProxySqlServerv2k5" name="Text6" id="0F5DC8AE-C3BF-2E97-D3DF-6A9C40C14B91">
<createdBy>peter</createdBy>
<createdTime>2015-04-07 07:49:32 UTC</createdTime>
<ownerDesignName>FeuerwehrDirect</ownerDesignName>
</ColumnProxy>
<ColumnProxy class="oracle.dbtools.crest.model.design.storage.sqlserver.v2k5.ColumnProxySqlServerv2k5" name="TUEV" id="12AE55BE-65CD-3A29-5E6F-244C3020F8D9">
<createdBy>peter</createdBy>
<createdTime>2015-04-07 07:49:32 UTC</createdTime>
<ownerDesignName>FeuerwehrDirect</ownerDesignName>
</ColumnProxy>
<ColumnProxy class="oracle.dbtools.crest.model.design.storage.sqlserver.v2k5.ColumnProxySqlServerv2k5" name="Datum1" id="16918F15-3E87-BD36-5E5E-9ABDF8A6F45E">
<createdBy>peter</createdBy>
<createdTime>2015-04-07 07:49:32 UTC</createdTime>
<ownerDesignName>FeuerwehrDirect</ownerDesignName>
</ColumnProxy>
<ColumnProxy class="oracle.dbtools.crest.model.design.storage.sqlserver.v2k5.ColumnProxySqlServerv2k5" name="Flaschenart" id="1FF20B27-60D1-7F03-F082-AF05559ED293">
<createdBy>peter</createdBy>
<createdTime>2015-04-07 07:49:32 UTC</createdTime>
<ownerDesignName>FeuerwehrDirect</ownerDesignName>
<defaultValue>N&apos;AG&apos;</defaultValue>
</ColumnProxy>
<ColumnProxy class="oracle.dbtools.crest.model.design.storage.sqlserver.v2k5.ColumnProxySqlServerv2k5" name="JaNein1" id="28C8D748-09FF-E535-F18A-EB217C6F516A">
<createdBy>peter</createdBy>
<createdTime>2015-04-07 07:49:32 UTC</createdTime>
<ownerDesignName>FeuerwehrDirect</ownerDesignName>
</ColumnProxy>
<ColumnProxy class="oracle.dbtools.crest.model.design.storage.sqlserver.v2k5.ColumnProxySqlServerv2k5" name="Text1" id="29E475AD-903A-2999-F542-984CEE88B063">
<createdBy>peter</createdBy>
<createdTime>2015-04-07 07:49:32 UTC</createdTime>
<ownerDesignName>FeuerwehrDirect</ownerDesignName>
</ColumnProxy>
<ColumnProxy class="oracle.dbtools.crest.model.design.storage.sqlserver.v2k5.ColumnProxySqlServerv2k5" name="Bemerkung" id="357136BA-4C4A-64FF-1122-2935F30D661D">
<createdBy>peter</createdBy>
<createdTime>2015-04-07 07:49:32 UTC</createdTime>
<ownerDesignName>FeuerwehrDirect</ownerDesignName>
</ColumnProxy>
<ColumnProxy class="oracle.dbtools.crest.model.design.storage.sqlserver.v2k5.ColumnProxySqlServerv2k5" name="Text5" id="35A91F61-0BA5-CBDF-E895-FA968260201F">
<createdBy>peter</createdBy>
<createdTime>2015-04-07 07:49:32 UTC</createdTime>
<ownerDesignName>FeuerwehrDirect</ownerDesignName>
</ColumnProxy>
<ColumnProxy class="oracle.dbtools.crest.model.design.storage.sqlserver.v2k5.ColumnProxySqlServerv2k5" name="Zahl3" id="3B0DA2B8-D8AD-B117-07FD-9F95A20E18F0">
<createdBy>peter</createdBy>
<createdTime>2015-04-07 07:49:32 UTC</createdTime>
<ownerDesignName>FeuerwehrDirect</ownerDesignName>
</ColumnProxy>
<ColumnProxy class="oracle.dbtools.crest.model.design.storage.sqlserver.v2k5.ColumnProxySqlServerv2k5" name="Text2" id="3DFDB1B2-5956-CD53-0641-0214BDA75E51">
<createdBy>peter</createdBy>
<createdTime>2015-04-07 07:49:32 UTC</createdTime>
<ownerDesignName>FeuerwehrDirect</ownerDesignName>
</ColumnProxy>
<ColumnProxy class="oracle.dbtools.crest.model.design.storage.sqlserver.v2k5.ColumnProxySqlServerv2k5" name="Druck" id="46225D50-2089-6B54-A11B-FCC32A937089">
<createdBy>peter</createdBy>
<createdTime>2015-04-07 07:49:32 UTC</createdTime>
<ownerDesignName>FeuerwehrDirect</ownerDesignName>
<defaultValue>0</defaultValue>
</ColumnProxy>
<ColumnProxy class="oracle.dbtools.crest.model.design.storage.sqlserver.v2k5.ColumnProxySqlServerv2k5" name="Zahl9" id="4975BEC9-B5E7-F451-A1AD-C5A61B1DC8D5">
<createdBy>peter</createdBy>
<createdTime>2015-04-07 07:49:32 UTC</createdTime>
<ownerDesignName>FeuerwehrDirect</ownerDesignName>
</ColumnProxy>
<ColumnProxy class="oracle.dbtools.crest.model.design.storage.sqlserver.v2k5.ColumnProxySqlServerv2k5" name="Zahl1" id="52A7B243-4E02-4A64-895A-9E3A71F30CBD">
<createdBy>peter</createdBy>
<createdTime>2015-04-07 07:49:32 UTC</createdTime>
<ownerDesignName>FeuerwehrDirect</ownerDesignName>
<defaultValue>0</defaultValue>
</ColumnProxy>
<ColumnProxy class="oracle.dbtools.crest.model.design.storage.sqlserver.v2k5.ColumnProxySqlServerv2k5" name="Inventarnummer" id="663F0958-B2C8-BB22-E2E5-9D276C2E1074">
<createdBy>peter</createdBy>
<createdTime>2015-04-07 07:49:32 UTC</createdTime>
<ownerDesignName>FeuerwehrDirect</ownerDesignName>
</ColumnProxy>
<ColumnProxy class="oracle.dbtools.crest.model.design.storage.sqlserver.v2k5.ColumnProxySqlServerv2k5" name="Text9" id="6982C4F3-9548-873E-D2AE-A4700782ABAD">
<createdBy>peter</createdBy>
<createdTime>2015-04-07 07:49:32 UTC</createdTime>
<ownerDesignName>FeuerwehrDirect</ownerDesignName>
</ColumnProxy>
<ColumnProxy class="oracle.dbtools.crest.model.design.storage.sqlserver.v2k5.ColumnProxySqlServerv2k5" name="Standort" id="69AF1562-7966-A844-307C-EBD6DF8215FD">
<createdBy>peter</createdBy>
<createdTime>2015-04-07 07:49:32 UTC</createdTime>
<ownerDesignName>FeuerwehrDirect</ownerDesignName>
</ColumnProxy>
<ColumnProxy class="oracle.dbtools.crest.model.design.storage.sqlserver.v2k5.ColumnProxySqlServerv2k5" name="Datum2" id="6A2BBA0C-FB80-A961-CA7F-FF3A3CF1961A">
<createdBy>peter</createdBy>
<createdTime>2015-04-07 07:49:32 UTC</createdTime>
<ownerDesignName>FeuerwehrDirect</ownerDesignName>
</ColumnProxy>
<ColumnProxy class="oracle.dbtools.crest.model.design.storage.sqlserver.v2k5.ColumnProxySqlServerv2k5" name="Letztes_Update" id="6A4ED850-E2D6-D01A-7FE1-1BB7D58D86AD">
<createdBy>peter</createdBy>
<createdTime>2015-04-07 07:49:32 UTC</createdTime>
<ownerDesignName>FeuerwehrDirect</ownerDesignName>
<defaultValue>=Now</defaultValue>
</ColumnProxy>
<ColumnProxy class="oracle.dbtools.crest.model.design.storage.sqlserver.v2k5.ColumnProxySqlServerv2k5" name="Text4" id="6C382993-BF3A-85E0-AB00-5B2871BAD6EE">
<createdBy>peter</createdBy>
<createdTime>2015-04-07 07:49:32 UTC</createdTime>
<ownerDesignName>FeuerwehrDirect</ownerDesignName>
</ColumnProxy>
<ColumnProxy class="oracle.dbtools.crest.model.design.storage.sqlserver.v2k5.ColumnProxySqlServerv2k5" name="Zahl2" id="75C64584-C6F0-7A21-802F-F48FE49C8D38">
<createdBy>peter</createdBy>
<createdTime>2015-04-07 07:49:32 UTC</createdTime>
<ownerDesignName>FeuerwehrDirect</ownerDesignName>
<defaultValue>0</defaultValue>
</ColumnProxy>
<ColumnProxy class="oracle.dbtools.crest.model.design.storage.sqlserver.v2k5.ColumnProxySqlServerv2k5" name="Zahl8" id="7A01334D-3DA7-7428-000D-202461A298A6">
<createdBy>peter</createdBy>
<createdTime>2015-04-07 07:49:32 UTC</createdTime>
<ownerDesignName>FeuerwehrDirect</ownerDesignName>
</ColumnProxy>
<ColumnProxy class="oracle.dbtools.crest.model.design.storage.sqlserver.v2k5.ColumnProxySqlServerv2k5" name="Zaehler" id="7AC144DF-2513-39E5-FD92-93DF8FBE109C">
<createdBy>peter</createdBy>
<createdTime>2015-04-07 07:49:32 UTC</createdTime>
<ownerDesignName>FeuerwehrDirect</ownerDesignName>
<asIdentity>true</asIdentity>
<identityForReplication>YES</identityForReplication>
</ColumnProxy>
<ColumnProxy class="oracle.dbtools.crest.model.design.storage.sqlserver.v2k5.ColumnProxySqlServerv2k5" name="Stadt" id="8093DEB8-5E4F-AEED-BC0A-D1073DA481D2">
<createdBy>peter</createdBy>
<createdTime>2015-04-07 07:49:32 UTC</createdTime>
<ownerDesignName>FeuerwehrDirect</ownerDesignName>
</ColumnProxy>
<ColumnProxy class="oracle.dbtools.crest.model.design.storage.sqlserver.v2k5.ColumnProxySqlServerv2k5" name="JaNein2" id="81F591DD-592A-7FD2-3AC3-72365A6EA3D5">
<createdBy>peter</createdBy>
<createdTime>2015-04-07 07:49:32 UTC</createdTime>
<ownerDesignName>FeuerwehrDirect</ownerDesignName>
</ColumnProxy>
<ColumnProxy class="oracle.dbtools.crest.model.design.storage.sqlserver.v2k5.ColumnProxySqlServerv2k5" name="Zahl6" id="889924C9-D2B6-4445-AF19-B93C4AB823C3">
<createdBy>peter</createdBy>
<createdTime>2015-04-07 07:49:32 UTC</createdTime>
<ownerDesignName>FeuerwehrDirect</ownerDesignName>
</ColumnProxy>
<ColumnProxy class="oracle.dbtools.crest.model.design.storage.sqlserver.v2k5.ColumnProxySqlServerv2k5" name="Preis" id="98210E73-0DC6-B6B0-7EE9-F6001759DDB4">
<createdBy>peter</createdBy>
<createdTime>2015-04-07 07:49:32 UTC</createdTime>
<ownerDesignName>FeuerwehrDirect</ownerDesignName>
<defaultValue>0</defaultValue>
</ColumnProxy>
<ColumnProxy class="oracle.dbtools.crest.model.design.storage.sqlserver.v2k5.ColumnProxySqlServerv2k5" name="Text8" id="9A15F555-8C54-7225-5AF5-6B4D23BC1894">
<createdBy>peter</createdBy>
<createdTime>2015-04-07 07:49:32 UTC</createdTime>
<ownerDesignName>FeuerwehrDirect</ownerDesignName>
</ColumnProxy>
<ColumnProxy class="oracle.dbtools.crest.model.design.storage.sqlserver.v2k5.ColumnProxySqlServerv2k5" name="Ort" id="B4E7FA5B-1F28-2610-A285-CF9F0EF3795F">
<createdBy>peter</createdBy>
<createdTime>2015-04-07 07:49:32 UTC</createdTime>
<ownerDesignName>FeuerwehrDirect</ownerDesignName>
</ColumnProxy>
<ColumnProxy class="oracle.dbtools.crest.model.design.storage.sqlserver.v2k5.ColumnProxySqlServerv2k5" name="Hersteller" id="C221BCF5-F180-7BB4-CA63-0FF6A68009F1">
<createdBy>peter</createdBy>
<createdTime>2015-04-07 07:49:32 UTC</createdTime>
<ownerDesignName>FeuerwehrDirect</ownerDesignName>
</ColumnProxy>
<ColumnProxy class="oracle.dbtools.crest.model.design.storage.sqlserver.v2k5.ColumnProxySqlServerv2k5" name="Lieferant" id="C32E16B2-565A-8F7F-442D-231B2C0C4AB3">
<createdBy>peter</createdBy>
<createdTime>2015-04-07 07:49:32 UTC</createdTime>
<ownerDesignName>FeuerwehrDirect</ownerDesignName>
</ColumnProxy>
<ColumnProxy class="oracle.dbtools.crest.model.design.storage.sqlserver.v2k5.ColumnProxySqlServerv2k5" name="Flaschennummer" id="CB8019FE-9010-AF93-A937-0395884A66DC">
<createdBy>peter</createdBy>
<createdTime>2015-04-07 07:49:32 UTC</createdTime>
<ownerDesignName>FeuerwehrDirect</ownerDesignName>
</ColumnProxy>
<ColumnProxy class="oracle.dbtools.crest.model.design.storage.sqlserver.v2k5.ColumnProxySqlServerv2k5" name="InDienstGestellt" id="CCBC0831-967C-8B51-3A37-28E1C170264C">
<createdBy>peter</createdBy>
<createdTime>2015-04-07 07:49:32 UTC</createdTime>
<ownerDesignName>FeuerwehrDirect</ownerDesignName>
</ColumnProxy>
<ColumnProxy class="oracle.dbtools.crest.model.design.storage.sqlserver.v2k5.ColumnProxySqlServerv2k5" name="Zahl5" id="D1CEB8F3-BBA0-5DF1-9625-D1B8F9DF8DA4">
<createdBy>peter</createdBy>
<createdTime>2015-04-07 07:49:32 UTC</createdTime>
<ownerDesignName>FeuerwehrDirect</ownerDesignName>
</ColumnProxy>
<ColumnProxy class="oracle.dbtools.crest.model.design.storage.sqlserver.v2k5.ColumnProxySqlServerv2k5" name="ausgesondert" id="D9E75EA6-FA5D-CC59-D3F2-B134830E0AA2">
<createdBy>peter</createdBy>
<createdTime>2015-04-07 07:49:32 UTC</createdTime>
<ownerDesignName>FeuerwehrDirect</ownerDesignName>
</ColumnProxy>
<ColumnProxy class="oracle.dbtools.crest.model.design.storage.sqlserver.v2k5.ColumnProxySqlServerv2k5" name="Volumen" id="DAB5A87E-AB5D-F519-5A34-0ECA27CEA2D5">
<createdBy>peter</createdBy>
<createdTime>2015-04-07 07:49:32 UTC</createdTime>
<ownerDesignName>FeuerwehrDirect</ownerDesignName>
<defaultValue>0</defaultValue>
</ColumnProxy>
<ColumnProxy class="oracle.dbtools.crest.model.design.storage.sqlserver.v2k5.ColumnProxySqlServerv2k5" name="Zahl10" id="E082A4DA-568A-43B9-3942-E86603094C5D">
<createdBy>peter</createdBy>
<createdTime>2015-04-07 07:49:32 UTC</createdTime>
<ownerDesignName>FeuerwehrDirect</ownerDesignName>
</ColumnProxy>
<ColumnProxy class="oracle.dbtools.crest.model.design.storage.sqlserver.v2k5.ColumnProxySqlServerv2k5" name="Herstellungsdatum" id="E41BD162-4CA5-A116-AC26-62FFFF826AC9">
<createdBy>peter</createdBy>
<createdTime>2015-04-07 07:49:32 UTC</createdTime>
<ownerDesignName>FeuerwehrDirect</ownerDesignName>
</ColumnProxy>
<ColumnProxy class="oracle.dbtools.crest.model.design.storage.sqlserver.v2k5.ColumnProxySqlServerv2k5" name="gehoertZu" id="E4CFB983-0225-484F-9D8B-3EF5CDB0B4BC">
<createdBy>peter</createdBy>
<createdTime>2015-04-07 07:49:32 UTC</createdTime>
<ownerDesignName>FeuerwehrDirect</ownerDesignName>
</ColumnProxy>
<ColumnProxy class="oracle.dbtools.crest.model.design.storage.sqlserver.v2k5.ColumnProxySqlServerv2k5" name="Text7" id="E549EE9D-C365-179A-B6F1-D8A2174F4AC6">
<createdBy>peter</createdBy>
<createdTime>2015-04-07 07:49:32 UTC</createdTime>
<ownerDesignName>FeuerwehrDirect</ownerDesignName>
</ColumnProxy>
<ColumnProxy class="oracle.dbtools.crest.model.design.storage.sqlserver.v2k5.ColumnProxySqlServerv2k5" name="Fabriknummer" id="E617900F-1984-F663-5836-6B54B37C9DB8">
<createdBy>peter</createdBy>
<createdTime>2015-04-07 07:49:32 UTC</createdTime>
<ownerDesignName>FeuerwehrDirect</ownerDesignName>
</ColumnProxy>
<ColumnProxy class="oracle.dbtools.crest.model.design.storage.sqlserver.v2k5.ColumnProxySqlServerv2k5" name="aussondern_bis" id="EFEDE9FA-0BDF-2EC9-CAE9-B69D96D97253">
<createdBy>peter</createdBy>
<createdTime>2015-04-07 07:49:32 UTC</createdTime>
<ownerDesignName>FeuerwehrDirect</ownerDesignName>
</ColumnProxy>
<ColumnProxy class="oracle.dbtools.crest.model.design.storage.sqlserver.v2k5.ColumnProxySqlServerv2k5" name="Katalog_ID" id="F8D60FCC-01FB-6FB4-FD22-4A721BB67C14">
<createdBy>peter</createdBy>
<createdTime>2015-04-07 07:49:32 UTC</createdTime>
<ownerDesignName>FeuerwehrDirect</ownerDesignName>
</ColumnProxy>
<ColumnProxy class="oracle.dbtools.crest.model.design.storage.sqlserver.v2k5.ColumnProxySqlServerv2k5" name="Text10" id="F941F434-534D-57DD-D9CD-BF2B1499C883">
<createdBy>peter</createdBy>
<createdTime>2015-04-07 07:49:32 UTC</createdTime>
<ownerDesignName>FeuerwehrDirect</ownerDesignName>
</ColumnProxy>
<ColumnProxy class="oracle.dbtools.crest.model.design.storage.sqlserver.v2k5.ColumnProxySqlServerv2k5" name="Zahl" id="F978503D-5083-5E17-3F22-7BC64572C348">
<createdBy>peter</createdBy>
<createdTime>2015-04-07 07:49:32 UTC</createdTime>
<ownerDesignName>FeuerwehrDirect</ownerDesignName>
<defaultValue>1</defaultValue>
</ColumnProxy>
<ColumnProxy class="oracle.dbtools.crest.model.design.storage.sqlserver.v2k5.ColumnProxySqlServerv2k5" name="Text3" id="FA0281FA-109B-F316-133F-53B177C823F7">
<createdBy>peter</createdBy>
<createdTime>2015-04-07 07:49:32 UTC</createdTime>
<ownerDesignName>FeuerwehrDirect</ownerDesignName>
</ColumnProxy>
<ColumnProxy class="oracle.dbtools.crest.model.design.storage.sqlserver.v2k5.ColumnProxySqlServerv2k5" name="Zahl4" id="FB95FD24-EB99-A506-03A1-B58438107EAF">
<createdBy>peter</createdBy>
<createdTime>2015-04-07 07:49:32 UTC</createdTime>
<ownerDesignName>FeuerwehrDirect</ownerDesignName>
</ColumnProxy>
</columnProxies>
<indexProxies>
<IndexProxy class="oracle.dbtools.crest.model.design.storage.sqlserver.v2k5.IndexProxySqlServerv2k5" name="Druckluftflaschen$Zahl" id="2049061A-C9D7-0341-7E08-A9D37412C8B5">
<createdBy>peter</createdBy>
<createdTime>2015-04-07 07:49:32 UTC</createdTime>
<ownerDesignName>FeuerwehrDirect</ownerDesignName>
<recomputeStatistics>ON</recomputeStatistics>
</IndexProxy>
<IndexProxy class="oracle.dbtools.crest.model.design.storage.sqlserver.v2k5.IndexProxySqlServerv2k5" name="Druckluftflaschen$Fabriknummer" id="3C6943B9-14FC-56A2-191A-DD32A391F38C">
<createdBy>peter</createdBy>
<createdTime>2015-04-07 07:49:32 UTC</createdTime>
<ownerDesignName>FeuerwehrDirect</ownerDesignName>
<recomputeStatistics>ON</recomputeStatistics>
</IndexProxy>
<IndexProxy class="oracle.dbtools.crest.model.design.storage.sqlserver.v2k5.IndexProxySqlServerv2k5" name="Druckluftflaschen$Flaschennummer" id="E2B45D59-F2D0-2BC8-EB77-6D7C1B7B3462">
<createdBy>peter</createdBy>
<createdTime>2015-04-07 07:49:32 UTC</createdTime>
<ownerDesignName>FeuerwehrDirect</ownerDesignName>
<recomputeStatistics>ON</recomputeStatistics>
</IndexProxy>
</indexProxies>
<uniqueKeys>
<UniqueKey class="oracle.dbtools.crest.model.design.storage.sqlserver.v2k5.UniqueProxySqlServerv2k5" name="Druckluftflaschen$Zaehler" id="B039D5F7-BA15-5928-BE96-99DB2BCA273E">
<createdBy>peter</createdBy>
<createdTime>2015-04-07 07:49:32 UTC</createdTime>
<ownerDesignName>FeuerwehrDirect</ownerDesignName>
</UniqueKey>
</uniqueKeys>
</TableProxySqlServerv2k5>